MANIFEST.in
README.md
debian_dependencies.txt
requirements.txt
requirements_build.txt
requirements_dev.txt
setup.py
version.txt
apimas/__init__.py
apimas/cmd.py
apimas/config.py
apimas/constructors.py
apimas/documents.py
apimas/errors.py
apimas/exceptions.py
apimas/tabmatch.py
apimas.egg-info/PKG-INFO
apimas.egg-info/SOURCES.txt
apimas.egg-info/dependency_links.txt
apimas.egg-info/entry_points.txt
apimas.egg-info/requires.txt
apimas.egg-info/top_level.txt
apimas/adapters/__init__.py
apimas/adapters/adapter.py
apimas/adapters/cookbooks.py
apimas/adapters/utils.py
apimas/cli/__init__.py
apimas/cli/adapter.py
apimas/cli/commands.py
apimas/cli/custom_types.py
apimas/clients/__init__.py
apimas/clients/adapter.py
apimas/clients/auth.py
apimas/clients/clients.py
apimas/clients/extensions.py
apimas/testing/__init__.py
apimas/testing/helpers.py
auto/builder/docker/home/bin/mkdeb