Metadata-Version: 1.0
Name: apimas
Version: 0.3.4
Summary: API Modelling And Serving
Home-page: UNKNOWN
Author: GRNET S.A.
Author-email: apimas@dev.grnet.gr
License: Affero GPL v3
Platform: UNKNOWN
